<?xml version="1.0" encoding="utf-8" ?>
<scpd xmlns="urn:schemas-upnp-org:service-1-0">
  <specVersion>
    <major>1</major>
    <minor>0</minor>
  </specVersion>
  <serviceStateTable>
    <stateVariable sendEvents="no">
      <name>HouseholdID</name>
      <dataType>string</dataType>
    </stateVariable>
    <stateVariable sendEvents="yes">
      <name>SettingsReplicationState</name>
      <dataType>string</dataType>
    </stateVariable>
    <stateVariable sendEvents="yes">
      <name>ZoneName</name>
      <dataType>string</dataType>
    </stateVariable>
    <stateVariable sendEvents="yes">
      <name>Icon</name>
      <dataType>string</dataType>
    </stateVariable>
    <stateVariable sendEvents="yes">
      <name>Invisible</name>
      <dataType>boolean</dataType>
    </stateVariable>
    <stateVariable sendEvents="yes">
      <name>IsZoneBridge</name>
      <dataType>boolean</dataType>
    </stateVariable>
    <stateVariable sendEvents="yes">
      <name>ChannelMapSet</name>
      <dataType>string</dataType>
    </stateVariable>
    <stateVariable sendEvents="no">
      <name>LEDState</name>
      <dataType>string</dataType>
      <allowedValueList>
        <allowedValue>On</allowedValue>
        <allowedValue>Off</allowedValue>
      </allowedValueList>
    </stateVariable>
    <stateVariable sendEvents="no">
      <name>SerialNumber</name>
      <dataType>string</dataType>
    </stateVariable>
    <stateVariable sendEvents="no">
      <name>SoftwareVersion</name>
      <dataType>string</dataType>
    </stateVariable>
    <stateVariable sendEvents="no">
      <name>DisplaySoftwareVersion</name>
      <dataType>string</dataType>
    </stateVariable>
    <stateVariable sendEvents="no">
      <name>HardwareVersion</name>
      <dataType>string</dataType>
    </stateVariable>
    <stateVariable sendEvents="no">
      <name>IPAddress</name>
      <dataType>string</dataType>
    </stateVariable>
    <stateVariable sendEvents="no">
      <name>MACAddress</name>
      <dataType>string</dataType>
    </stateVariable>
    <stateVariable sendEvents="no">
      <name>CopyrightInfo</name>
      <dataType>string</dataType>
    </stateVariable>
    <stateVariable sendEvents="no">
      <name>ExtraInfo</name>
      <dataType>string</dataType>
    </stateVariable>
    <stateVariable sendEvents="no">
      <name>AutoplayIncludeLinkedZones</name>
      <dataType>boolean</dataType>
    </stateVariable>
    <stateVariable sendEvents="no">
      <name>AutoplayRoomUUID</name>
      <dataType>string</dataType>
    </stateVariable>
    <stateVariable sendEvents="no">
      <name>AutoplayVolume</name>
      <dataType>ui2</dataType>
      <allowedValueRange>
        <minimum>0</minimum>
        <maximum>100</maximum>
        <step>1</step>
      </allowedValueRange>
    </stateVariable>
    <stateVariable sendEvents="no">
      <name>A_ARG_TYPE_SettingID</name>
      <dataType>ui4</dataType>
      <allowedValueRange>
        <minimum>0</minimum>
        <maximum>65535</maximum>
      </allowedValueRange>
    </stateVariable>
    <stateVariable sendEvents="no">
      <name>A_ARG_TYPE_SettingURI</name>
      <dataType>string</dataType>
    </stateVariable>
    <stateVariable sendEvents="no">
      <name>AutoplayUseVolume</name>
      <dataType>boolean</dataType>
    </stateVariable>
  </serviceStateTable>
  <actionList>
    <action>
      <name>SetLEDState</name>
      <argumentList>
        <argument>
          <name>DesiredLEDState</name>
          <direction>in</direction>
          <relatedStateVariable>LEDState</relatedStateVariable>
        </argument>
      </argumentList>
    </action>
    <action>
      <name>GetLEDState</name>
      <argumentList>
        <argument>
          <name>CurrentLEDState</name>
          <direction>out</direction>
          <relatedStateVariable>LEDState</relatedStateVariable>
        </argument>
      </argumentList>
    </action>
    <action>
      <name>SetInvisible</name>
      <argumentList>
        <argument>
          <name>DesiredInvisible</name>
          <direction>in</direction>
          <relatedStateVariable>Invisible</relatedStateVariable>
        </argument>
      </argumentList>
    </action>
    <action>
      <name>GetInvisible</name>
      <argumentList>
        <argument>
          <name>CurrentInvisible</name>
          <direction>out</direction>
          <relatedStateVariable>Invisible</relatedStateVariable>
        </argument>
      </argumentList>
    </action>
    <action>
      <name>AddBondedZones</name>
      <argumentList>
        <argument>
          <name>ChannelMapSet</name>
          <direction>in</direction>
          <relatedStateVariable>ChannelMapSet</relatedStateVariable>
        </argument>
      </argumentList>
    </action>
    <action>
      <name>RemoveBondedZones</name>
      <argumentList>
        <argument>
          <name>ChannelMapSet</name>
          <direction>in</direction>
          <relatedStateVariable>ChannelMapSet</relatedStateVariable>
        </argument>
      </argumentList>
    </action>
    <action>
      <name>CreateStereoPair</name>
      <argumentList>
        <argument>
          <name>ChannelMapSet</name>
          <direction>in</direction>
          <relatedStateVariable>ChannelMapSet</relatedStateVariable>
        </argument>
      </argumentList>
    </action>
    <action>
      <name>SeparateStereoPair</name>
      <argumentList>
        <argument>
          <name>ChannelMapSet</name>
          <direction>in</direction>
          <relatedStateVariable>ChannelMapSet</relatedStateVariable>
        </argument>
      </argumentList>
    </action>
    <action>
      <name>SetZoneAttributes</name>
      <argumentList>
        <argument>
          <name>DesiredZoneName</name>
          <direction>in</direction>
          <relatedStateVariable>ZoneName</relatedStateVariable>
        </argument>
        <argument>
          <name>DesiredIcon</name>
          <direction>in</direction>
          <relatedStateVariable>Icon</relatedStateVariable>
        </argument>
      </argumentList>
    </action>
    <action>
      <name>GetZoneAttributes</name>
      <argumentList>
        <argument>
          <name>CurrentZoneName</name>
          <direction>out</direction>
          <relatedStateVariable>ZoneName</relatedStateVariable>
        </argument>
        <argument>
          <name>CurrentIcon</name>
          <direction>out</direction>
          <relatedStateVariable>Icon</relatedStateVariable>
        </argument>
      </argumentList>
    </action>
    <action>
      <name>GetHouseholdID</name>
      <argumentList>
        <argument>
          <name>CurrentHouseholdID</name>
          <direction>out</direction>
          <relatedStateVariable>HouseholdID</relatedStateVariable>
        </argument>
      </argumentList>
    </action>
    <action>
      <name>GetZoneInfo</name>
      <argumentList>
        <argument>
          <name>SerialNumber</name>
          <direction>out</direction>
          <relatedStateVariable>SerialNumber</relatedStateVariable>
        </argument>
        <argument>
          <name>SoftwareVersion</name>
          <direction>out</direction>
          <relatedStateVariable>SoftwareVersion</relatedStateVariable>
        </argument>
        <argument>
          <name>DisplaySoftwareVersion</name>
          <direction>out</direction>
          <relatedStateVariable>DisplaySoftwareVersion</relatedStateVariable>
        </argument>
        <argument>
          <name>HardwareVersion</name>
          <direction>out</direction>
          <relatedStateVariable>HardwareVersion</relatedStateVariable>
        </argument>
        <argument>
          <name>IPAddress</name>
          <direction>out</direction>
          <relatedStateVariable>IPAddress</relatedStateVariable>
        </argument>
        <argument>
          <name>MACAddress</name>
          <direction>out</direction>
          <relatedStateVariable>MACAddress</relatedStateVariable>
        </argument>
        <argument>
          <name>CopyrightInfo</name>
          <direction>out</direction>
          <relatedStateVariable>CopyrightInfo</relatedStateVariable>
        </argument>
        <argument>
          <name>ExtraInfo</name>
          <direction>out</direction>
          <relatedStateVariable>ExtraInfo</relatedStateVariable>
        </argument>
      </argumentList>
    </action>
    <action>
      <name>SetAutoplayLinkedZones</name>
      <argumentList>
        <argument>
          <name>IncludeLinkedZones</name>
          <direction>in</direction>
          <relatedStateVariable>AutoplayIncludeLinkedZones</relatedStateVariable>
        </argument>
      </argumentList>
    </action>
    <action>
      <name>GetAutoplayLinkedZones</name>
      <argumentList>
        <argument>
          <name>IncludeLinkedZones</name>
          <direction>out</direction>
          <relatedStateVariable>AutoplayIncludeLinkedZones</relatedStateVariable>
        </argument>
      </argumentList>
    </action>
    <action>
      <name>SetAutoplayRoomUUID</name>
      <argumentList>
        <argument>
          <name>RoomUUID</name>
          <direction>in</direction>
          <relatedStateVariable>AutoplayRoomUUID</relatedStateVariable>
        </argument>
      </argumentList>
    </action>
    <action>
      <name>GetAutoplayRoomUUID</name>
      <argumentList>
        <argument>
          <name>RoomUUID</name>
          <direction>out</direction>
          <relatedStateVariable>AutoplayRoomUUID</relatedStateVariable>
        </argument>
      </argumentList>
    </action>
    <action>
      <name>SetAutoplayVolume</name>
      <argumentList>
        <argument>
          <name>Volume</name>
          <direction>in</direction>
          <relatedStateVariable>AutoplayVolume</relatedStateVariable>
        </argument>
      </argumentList>
    </action>
    <action>
      <name>GetAutoplayVolume</name>
      <argumentList>
        <argument>
          <name>CurrentVolume</name>
          <direction>out</direction>
          <relatedStateVariable>AutoplayVolume</relatedStateVariable>
        </argument>
      </argumentList>
    </action>
    <action>
      <name>ImportSetting</name>
      <argumentList>
        <argument>
          <name>SettingID</name>
          <direction>in</direction>
          <relatedStateVariable>A_ARG_TYPE_SettingID</relatedStateVariable>
        </argument>
        <argument>
          <name>SettingURI</name>
          <direction>in</direction>
          <relatedStateVariable>A_ARG_TYPE_SettingURI</relatedStateVariable>
        </argument>
      </argumentList>
    </action>
    <action>
      <name>SetUseAutoplayVolume</name>
      <argumentList>
        <argument>
          <name>UseVolume</name>
          <direction>in</direction>
          <relatedStateVariable>AutoplayUseVolume</relatedStateVariable>
        </argument>
      </argumentList>
    </action>
    <action>
      <name>GetUseAutoplayVolume</name>
      <argumentList>
        <argument>
          <name>UseVolume</name>
          <direction>out</direction>
          <relatedStateVariable>AutoplayUseVolume</relatedStateVariable>
        </argument>
      </argumentList>
    </action>
  </actionList>
</scpd>
